LEGENDARY_CREATURE_CITY_BUILDER/legendary_creature_city_builder.py
LEGENDARY_CREATURE_CITY_BUILDER/legendary_creature_city_builder_tests.py
LEGENDARY_CREATURE_CITY_BUILDER-1.dist-info/LICENSE
LEGENDARY_CREATURE_CITY_BUILDER-1.dist-info/METADATA
LEGENDARY_CREATURE_CITY_BUILDER-1.dist-info/WHEEL
LEGENDARY_CREATURE_CITY_BUILDER-1.dist-info/entry_points.txt
LEGENDARY_CREATURE_CITY_BUILDER-1.dist-info/top_level.txt
LEGENDARY_CREATURE_CITY_BUILDER-1.dist-info/RECORD
