Metadata-Version: 2.1
Name: LEGENDARY-CREATURE-CITY-BUILDER
Version: 1
Summary: This package contains implementation of the offline strategy RPG "LEGENDARY_CREATURE_CITY_BUILDER" on command line interface.
Home-page: https://github.com/NativeApkDev/LEGENDARY_CREATURE_CITY_BUILDER
Author: NativeApkDev
Author-email: nativeapkdev2021@gmail.com
License: MIT
Platform: UNKNOWN
Classifier: Programming Language :: Python :: 3
Classifier: Programming Language :: Python :: 3.7
